{"chart":{"result":[{"meta":{"currency":"GBP","symbol":"0P0000X1Y6.L","exchangeName":"LSE","fullExchangeName":"LSE","instrumentType":"MUTUALFUND","firstTradeDate":1514880000,"regularMarketTime":1738958400,"hasPrePostMarketData":false,"gmtoffset":0,"timezone":"GMT","exchangeTimezoneName":"Europe/London","regularMarketPrice":2.832,"fiftyTwoWeekHigh":1.979,"fiftyTwoWeekLow":1.419,"longName":"Royal London UK Dividend Growth M","shortName":"Royal London UK Dividend Growth","chartPreviousClose":0.0,"priceHint":4,"currentTradingPeriod":{"pre":{"timezone":"GMT","end":1738915200,"start":1738912500,"gmtoffset":0},"regular":{"timezone":"GMT","end":1738945800,"start":1738915200,"gmtoffset":0},"post":{"timezone":"GMT","end":1738948500,"start":1738945800,"gmtoffset":0}},"dataGranularity":"1d","range":"","validRanges":["1mo","3mo","6mo","ytd","1y","2y","5y","10y","max"]},"timestamp":[1738915200],"events":{"dividends":{"1738915200":{"amount":0.017329,"date":1733126400}}},"indicators":{"quote":[{"low":[2.8320000171661377],"volume":[0],"open":[2.8320000171661377],"high":[2.8320000171661377],"close":[2.8320000171661377]}],"adjclose":[{"adjclose":[2.8320000171661377]}]}}],"error":null}}